tiferet_fast/__init__.py
tiferet_fast/contexts/__init__.py
tiferet_fast/contexts/fast.py
tiferet_fast/contexts/request.py
tiferet_fast/contracts/__init__.py
tiferet_fast/contracts/fast.py
tiferet_fast/data/__init__.py
tiferet_fast/data/fast.py
tiferet_fast/handlers/__init__.py
tiferet_fast/handlers/fast.py
tiferet_fast/models/__init__.py
tiferet_fast/models/fast.py
tiferet_fast/proxies/__init__.py
tiferet_fast/proxies/yaml/__init__.py
tiferet_fast/proxies/yaml/fast.py
tiferet_fast-0.1.0.dist-info/licenses/LICENSE
tiferet_fast-0.1.0.dist-info/METADATA
tiferet_fast-0.1.0.dist-info/WHEEL
tiferet_fast-0.1.0.dist-info/top_level.txt
tiferet_fast-0.1.0.dist-info/RECORD
