Metadata-Version: 2.4
Name: tiferet-fast
Version: 0.1.0
Summary: An extension of the Tiferet Framework for the Fast API.
Author-email: "Andrew Shatz, Great Strength Systems" <andrew@greatstrength.me>
License: MIT
Project-URL: Homepage, https://github.com/greatstrength/tiferet-fast
Project-URL: Repository, https://github.com/greatstrength/tiferet-fast
Project-URL: Download, https://github.com/greatstrength/tiferet-fast
Requires-Python: >=3.10
License-File: LICENSE
Requires-Dist: tiferet>=1.1.2
Requires-Dist: fastapi>=0.118.0
Requires-Dist: starlette-context>=0.4.0
Provides-Extra: test
Requires-Dist: pytest>=8.3.3; extra == "test"
Requires-Dist: pytest_env>=1.1.5; extra == "test"
Dynamic: license-file
